MANIFEST.in
README.md
setup.py
epynet/__init__.py
epynet/baseobject.py
epynet/curve.py
epynet/epanet2.py
epynet/lazy_property.py
epynet/link.py
epynet/network.py
epynet/node.py
epynet/objectcollection.py
epynet/pattern.py
epynet.egg-info/PKG-INFO
epynet.egg-info/SOURCES.txt
epynet.egg-info/dependency_links.txt
epynet.egg-info/not-zip-safe
epynet.egg-info/requires.txt
epynet.egg-info/top_level.txt
epynet/lib/epanet2.dll
epynet/lib/libepanet.dylib
epynet/lib/libepanet.so