Metadata-Version: 1.0
Name: epynet
Version: 1.0
Summary: Vitens EPANET 2.0 wrapper and utilities
Home-page: https://github.com/vitens/epynet
Author: Abel Heinsbroek
Author-email: abel.heinsbroek@vitens.nl
License: Apache Licence 2.0
Platform: UNKNOWN
